hallett/__init__.py
hallett/core.py
hallett-0.0.0.dev0.dist-info/licenses/LICENSE
hallett-0.0.0.dev0.dist-info/METADATA
hallett-0.0.0.dev0.dist-info/WHEEL
hallett-0.0.0.dev0.dist-info/top_level.txt
hallett-0.0.0.dev0.dist-info/RECORD
